CHANGES.rst
LICENSE.rst
MANIFEST.in
README.rst
setup.py
src/yafowil/__init__.py
src/yafowil.lingua.egg-info/PKG-INFO
src/yafowil.lingua.egg-info/SOURCES.txt
src/yafowil.lingua.egg-info/dependency_links.txt
src/yafowil.lingua.egg-info/entry_points.txt
src/yafowil.lingua.egg-info/namespace_packages.txt
src/yafowil.lingua.egg-info/not-zip-safe
src/yafowil.lingua.egg-info/requires.txt
src/yafowil.lingua.egg-info/top_level.txt
src/yafowil/lingua/__init__.py
src/yafowil/lingua/extractor.py
src/yafowil/lingua/tests.py