Metadata-Version: 1.1
Name: yafowil.lingua
Version: 1.0
Summary: YAFOWIL - Lingua message extrator for yafowil.yaml based forms.
Home-page: http://pypi.python.org/pypi/yafowil.lingua
Author: BlueDynamics Alliance
Author-email: dev@bluedynamics.com
License: BSD
Keywords: html input widgets form compound
Platform: UNKNOWN
Classifier: Operating System :: OS Independent
Classifier: Programming Language :: Python
Classifier: Topic :: Software Development
Classifier: Topic :: Internet :: WWW/HTTP :: Dynamic Content
Classifier: License :: OSI Approved :: BSD License
